halcon/__init__.py
halcon/search.py
halcon-1.0.0.dist-info/AUTHORS
halcon-1.0.0.dist-info/LICENSE
halcon-1.0.0.dist-info/METADATA
halcon-1.0.0.dist-info/WHEEL
halcon-1.0.0.dist-info/top_level.txt
halcon-1.0.0.dist-info/RECORD
