Metadata-Version: 2.1
Name: halcon
Version: 1.0.0
Summary: Python implementation of FALCON: Feedback Adaptive Loop for Content-Based Retrieval
Author: Ivan E. Cao-Berg
Author-email: icaoberg@alumni.cmu.edu
Project-URL: Bug Tracker, https://github.com/icaoberg/falcon
Project-URL: Documentation, https://github.com/icaoberg/falcon-docs
Project-URL: Source Code, https://github.com/icaoberg/falcon
Classifier: Programming Language :: Python :: 3
Classifier: Intended Audience :: Science/Research
Classifier: Intended Audience :: Developers
Classifier: Intended Audience :: Information Technology
Classifier: Topic :: Scientific/Engineering :: Bio-Informatics
Classifier: Topic :: Scientific/Engineering :: Information Analysis
Classifier: License :: OSI Approved :: GNU Library or Lesser General Public License (LGPL)
Classifier: Operating System :: OS Independent
Classifier: Development Status :: 5 - Production/Stable
Requires-Python: >=3.6
License-File: LICENSE
License-File: AUTHORS
